neurum/__init__.py
neurum/ask.py
neurum-2.4.8.dist-info/LICENSE.txt
neurum-2.4.8.dist-info/METADATA
neurum-2.4.8.dist-info/WHEEL
neurum-2.4.8.dist-info/top_level.txt
neurum-2.4.8.dist-info/RECORD
