Metadata-Version: 2.1
Name: neurum
Version: 2.4.8
Summary: A powerful multimodal AI sdk for python by Neurum Inc..
Home-page: https://github.com/VanshShah1/notion
Author: Vansh Shah
Author-email: vanshshah836@gmail.com
Keywords: ai api sdk llm
Classifier: Development Status :: 2 - Pre-Alpha
Classifier: Intended Audience :: Developers
Classifier: Operating System :: MacOS :: MacOS X
Classifier: Operating System :: Microsoft :: Windows
Classifier: Operating System :: Unix
Classifier: License :: OSI Approved :: MIT License
Classifier: Programming Language :: Python
License-File: LICENSE.txt
Requires-Dist: quickjs
